rm_lines/__init__.py
rm_lines/inker/__init__.py
rm_lines/inker/document_size_tracker.py
rm_lines/inker/svg.py
rm_lines/inker/writing_tools.py
rm_lines/rmscene/LICENSE
rm_lines/rmscene/__init__.py
rm_lines/rmscene/__main__.py
rm_lines/rmscene/crdt_sequence.py
rm_lines/rmscene/py.typed
rm_lines/rmscene/scene_items.py
rm_lines/rmscene/scene_stream.py
rm_lines/rmscene/scene_tree.py
rm_lines/rmscene/tagged_block_common.py
rm_lines/rmscene/tagged_block_reader.py
rm_lines/rmscene/tagged_block_writer.py
rm_lines/rmscene/text.py
rm_lines/writer/__init__.py
rm_lines-1.0.2.dist-info/METADATA
rm_lines-1.0.2.dist-info/WHEEL
rm_lines-1.0.2.dist-info/RECORD
