Metadata-Version: 2.3
Name: rm-lines
Version: 1.0.2
Summary: A python library that combines rmscene/rmc and librm_lines to read and render rM Line files
License: Mixed
Author: RedTTG
Author-email: red@redttg.com
Requires-Python: >=3.9
Classifier: License :: Other/Proprietary License
Classifier: Programming Language :: Python :: 3
Classifier: Programming Language :: Python :: 3.9
Classifier: Programming Language :: Python :: 3.10
Classifier: Programming Language :: Python :: 3.11
Classifier: Programming Language :: Python :: 3.12
Classifier: Programming Language :: Python :: 3.13
Requires-Dist: colorama (>=0.4.6,<0.5.0)
Requires-Dist: rm-api (>=1.0.0,<2.0.0)
